LICENSE.txt
setup.py
Topsis_Aneesh_101903395.egg-info/PKG-INFO
Topsis_Aneesh_101903395.egg-info/SOURCES.txt
Topsis_Aneesh_101903395.egg-info/dependency_links.txt
Topsis_Aneesh_101903395.egg-info/requires.txt
Topsis_Aneesh_101903395.egg-info/top_level.txt
topsis/topsis-101903395.py